ua_extract/__init__.py
ua_extract/__main__.py
ua_extract/cli.py
ua_extract/configure_regex_interpolators.sh
ua_extract/device_detector.py
ua_extract/enums.py
ua_extract/lazy_regex.py
ua_extract/settings.py
ua_extract/update_regex.py
ua_extract/utils.py
ua_extract/warnings.py
ua_extract/yaml_loader.py
ua_extract/appdetails/__init__.py
ua_extract/appdetails/ai.yml
ua_extract/appdetails/av.yml
ua_extract/appdetails/browser.yml
ua_extract/appdetails/desktop_app.yml
ua_extract/appdetails/game.yml
ua_extract/appdetails/library.yml
ua_extract/appdetails/mediaplayer.yml
ua_extract/appdetails/messaging.yml
ua_extract/appdetails/mobile_app.yml
ua_extract/appdetails/navigation.yml
ua_extract/appdetails/osutility.yml
ua_extract/appdetails/p2p.yml
ua_extract/appdetails/pim.yml
ua_extract/appdetails/productivity.yml
ua_extract/appdetails/vpnproxy.yml
ua_extract/parser/__init__.py
ua_extract/parser/client_hints.py
ua_extract/parser/extractors.py
ua_extract/parser/key_value_pairs.py
ua_extract/parser/operating_system.py
ua_extract/parser/os_fragment.py
ua_extract/parser/parser.py
ua_extract/parser/settings.py
ua_extract/parser/client/__init__.py
ua_extract/parser/client/adobe_cc.py
ua_extract/parser/client/base.py
ua_extract/parser/client/browser.py
ua_extract/parser/client/desktopapp.py
ua_extract/parser/client/dictua.py
ua_extract/parser/client/extractor_name_version.py
ua_extract/parser/client/extractor_whole_name.py
ua_extract/parser/client/feed_reader.py
ua_extract/parser/client/library.py
ua_extract/parser/client/mediaplayer.py
ua_extract/parser/client/messaging.py
ua_extract/parser/client/mobileapp.py
ua_extract/parser/client/pim.py
ua_extract/parser/client/vpnproxy.py
ua_extract/parser/client/hints/__init__.py
ua_extract/parser/client/hints/browser.py
ua_extract/parser/client/hints/mobileapp.py
ua_extract/parser/device/__init__.py
ua_extract/parser/device/base.py
ua_extract/parser/device/bot.py
ua_extract/parser/device/camera.py
ua_extract/parser/device/car_browser.py
ua_extract-1.3.2.dist-info/LICENSE
ua_extract-1.3.2.dist-info/METADATA
ua_extract-1.3.2.dist-info/WHEEL
ua_extract-1.3.2.dist-info/entry_points.txt
ua_extract-1.3.2.dist-info/top_level.txt
ua_extract-1.3.2.dist-info/zip-safe
ua_extract-1.3.2.dist-info/RECORD
