Metadata-Version: 2.1
Name: ua_extract
Version: 1.3.2
Summary: Python3 port of matomo's Device Detector
Home-page: https://github.com/pranavagrawal321/ua_extract
Author: Pranav Agrawal
Author-email: pranavagrawal321@gmail.com
License: MIT
Project-URL: Source, https://github.com/pranavagrawal321/ua_extract
Project-URL: Issues, https://github.com/pranavagrawal321/ua_extract/issues
Project-URL: Documentation, https://github.com/pranavagrawal321/ua_extract#readme
Classifier: Environment :: Web Environment
Classifier: Intended Audience :: Developers
Classifier: Operating System :: OS Independent
Classifier: License :: OSI Approved :: MIT License
Classifier: Programming Language :: Python
Classifier: Topic :: Internet :: WWW/HTTP
Classifier: Topic :: Software Development :: Libraries :: Python Modules
Classifier: Programming Language :: Python :: 3.10
Classifier: Programming Language :: Python :: 3.11
Classifier: Programming Language :: Python :: 3.12
Classifier: Programming Language :: Python :: 3.13
Classifier: Programming Language :: Python :: 3.14
Classifier: Programming Language :: Python :: Implementation :: CPython
Classifier: Topic :: Internet :: WWW/HTTP
Classifier: Topic :: Software Development :: Libraries :: Python Modules
Requires-Python: >=3.10
License-File: LICENSE
Requires-Dist: ahocorasick-rs
Requires-Dist: pyyaml
Requires-Dist: regex
Requires-Dist: aiohttp
Requires-Dist: tenacity
Requires-Dist: rich
Requires-Dist: exrex
Requires-Dist: typer
Requires-Dist: backports.strenum ; python_version <= "3.10"
Requires-Dist: typing-extensions ; python_version <= "3.10"
